{"inkVersion":21,"root":[[{"->":"meet_conc"},["done",{"#f":5,"#n":"g-0"}],null],"done",{"meet_conc":[["^'It's... a ghost?'","\n","^'Strange; there were only ever murmurs of monsters, never ghosts.'","\n","^\"Welcome to my estate.\"","\n","^\"I hope you made preparations for your disappearance.\"","\n","^\"It's ineviatable, really.\"","\n","^\"I've yet to see someone come out.\"","\n","^\"But, nevermind that.\"","\n","^\"You've crossed the threshold, so there's no turning back for you now.\"","\n","^\"Are you ready?\"","\n","ev","str","^\"Yes\"","/str","/ev",{"*":".^.c-0","flg":4},"ev","str","^\"No\"","/str","/ev",{"*":".^.c-1","flg":4},"ev","str","^\"Something\"","/str","/ev",{"*":".^.c-2","flg":4},"ev","str","^\"Sorry\"","/str","/ev",{"*":".^.c-3","flg":4},{"c-0":["^ ",{"->":"red_str"},"\n",{"#f":5}],"c-1":["^ ",{"->":"unfortunate"},"\n","^\"...\"","\n","^\"...\"","\n","^\"Perhaps not.\"","\n","^\"...\"","\n","^\"...\"","\n","^\"...\"","\n","^\"This... is awkward...\"","\n","^\"...\"","\n","^\"...\"","\n","^\"Please, say something.\"","\n","^\"I don't enjoy people staring at me.\"","\n",{"#f":5}],"c-2":["^ ",{"->":"ha"},"\n",{"#f":5}],"c-3":["^ ",{"->":"thank"},"\n","^...","\n",{"#f":5}]}],{"#f":1}],"thank":["^\"Thank you.\"","\n",{"->":"ready"},{"#f":1}],"ha":["^\"Ha. How humorous.\"","\n",{"->":"ready"},{"#f":1}],"red_str":["^\"Good.\"","\n",{"->":"ready"},{"#f":1}],"ready":[["^\"Before you go in, we have some rules. Listen carefully.\"","\n","^\"You can touch, inspect, and ignore the items and furniture in the property, but you cannot take anything with you.\"","\n","^\"The estate must remain as it is.\"","\n","^\"I see you have a notebook with you - should you choose to inspect and make note of something make sure to press 'N' to see what you've written down.\"","\n","^\"And please, don't drop your pen on the floor.\"","\n","^\"There will be no food or refreshments inside, so I hope you've come with a satiated appetite.\"","\n","^\"Once you meet an inhabitant you cannot leave unless they allow you to leave.\"","\n","^\"They tend to monologue, and some enjoy the interjection while others want to be heard in full.\"","\n","^\"Pick your responses carefully, as once they are no longer relavent to the conversation they will disappear.\"","\n","^\"Some are more easily agitated than others.\"","\n","^\"And most importantly, your life will be on the line with each monster you meet.\"","\n","^\"Do you understand?\"","\n","ev","str","^Yes","/str","/ev",{"*":".^.c-0","flg":4},"ev","str","^No","/str","/ev",{"*":".^.c-1","flg":4},{"c-0":["^ ",{"->":"enter"},"\n",{"#f":5}],"c-1":["^ ",{"->":"rep_ready"},"\n",{"#f":5}]}],{"#f":1}],"unfortunate":["^\"Oh my.\"","\n","^\"Unfortunately you've already passed through the gates, so leaving is no longer an option.\"","\n","^\"No matter; I will prepare you as best as I can.\"","\n",{"->":"ready"},{"#f":1}],"enter":["^\"Good.\"","\n","^\"It is time I take my leave.\"","\n","^\"Make sure to hold onto your notepad tightly.\"","\n","^\"Things are known to get lost in the fray.\"","\n","end",{"#f":1}],"rep_ready":[["^\"I will repeat myself once more.\"","\n","^\"Listen carefully, because I will not repeat myself again.\"","\n","^\"You can touch, inspect, and ignore the items and furniture in the property, but you cannot take anything with you.\"","\n","^\"The estate must remain as it was and as it is.\"","\n","^\"Should you choose to inspect and make note of something, make sure to press 'N' to see what you've written down.\"","\n","^\"And please, don't drop your pen on the floor.\"","\n","^\"There will be no food or refreshments inside, so I hope you've come with a satiated appetite.\"","\n","ev","str","^Why?","/str","/ev",{"*":".^.c-0","flg":4},"ev","str","^Yes","/str","/ev",{"*":".^.c-1","flg":4},"ev","str","^No","/str","/ev",{"*":".^.c-2","flg":4},{"c-0":["^ ",{"->":"why"},"\n","^\"Once you meet an inhabitant you cannot leave unless they allow you to leave.\"","\n","^\"They tend to monologue, and some enjoy the interjection while others want to be heard in full.\"","\n","^\"Pick your responses carefully; if you take too long, your response will no longer be relavent and you will not be able to reply with the options you were provided.\"","\n","^\"Sometimes not responding is beneficial. Other times, it can be to your detriment.\"","\n","^\"And most importantly, your life will be on the line with each inhabitant you meet.\"","\n","^\"Do you understand?\"","\n",{"#f":5}],"c-1":["^ ",{"->":"enter"},"\n",{"#f":5}],"c-2":["^ ",{"->":"rep_ag"},"\n",{"#f":5}]}],{"#f":1}],"rep_ag":["^\"Too bad.\"","\n","^\"It is time for you to enter.\"","\n","^\"Good luck, and keep a tight grip on that notepad of yours.\"","\n","^\"Things are known to get lost in the fray.\"","\n","end",{"#f":1}],"why":["^\"I-\"","\n","^\"Please, let me finish.\"","\n","^\"I want to make sure you understand the gravity of the situation you are about to enter.\"","\n",{"->":"again"},{"#f":1}],"again":["^\"Once you meet an inhabitant you cannot leave unless they allow you to leave.\"","\n","^\"They tend to monologue, and some enjoy the interjection while others want to be heard in full.\"","\n","^\"Pick your responses carefully; if you take too long, your response will no longer be relavent and you will not be able to reply with the options you were provided.\"","\n","^\"Sometimes not responding is beneficial. Other times, it can be to your detriment.\"","\n","^\"And most importantly, your life will be on the line with each inhabitant you meet.\"","\n","^\"...\"","\n","^\"I hope you are ready, as it is time for me to take my leave.\"","\n","^\"Good luck, and keep your notepoad close.\"","\n","^\"Things are known to get lost in the fray.\"","\n","end",{"#f":1}],"#f":1}],"listDefs":{}}